fmfexporter/__init__.py
fmfexporter/fmf_adapter.py
fmfexporter/fmf_testcase.py
fmfexporter/adapters/__init__.py
fmfexporter/adapters/polarion/__init__.py
fmfexporter/adapters/polarion/fmf_adapter_polarion.py
fmfexporter/adapters/polarion/polarion_reporter.py
fmfexporter/adapters/polarion/polarion_test_case.py
fmfexporter/adapters/polarion/args/__init__.py
fmfexporter/adapters/polarion/args/polarion_args_parser.py
fmfexporter/adapters/polarion/connectors/__init__.py
fmfexporter/adapters/polarion/connectors/jira/__init__.py
fmfexporter/adapters/polarion/connectors/jira/fmf_jira.py
fmfexporter/adapters/polarion/utils/__init__.py
fmfexporter/adapters/polarion/utils/polarion_config.py
fmfexporter/adapters/polarion/utils/polarion_xml.py
fmfexporter/args/__init__.py
fmfexporter/args/args_parser.py
fmfexporter/metadata/__init__.py
fmfexporter/metadata/approvals.fmf
fmfexporter/metadata/authors.fmf
fmfexporter/metadata/components.fmf
fmfexporter/metadata/description.fmf
fmfexporter/metadata/estimate.fmf
fmfexporter/metadata/importance.fmf
fmfexporter/metadata/level.fmf
fmfexporter/metadata/parameters.fmf
fmfexporter/metadata/properties.fmf
fmfexporter/metadata/subcomponents.fmf
fmfexporter/metadata/summary.fmf
fmfexporter/metadata/tags.fmf
fmfexporter/metadata/test-steps.fmf
fmfexporter/metadata/type.fmf
fmfexporter/metadata/.fmf/version
fmfexporter/metadata/adapter/main.fmf
fmfexporter/metadata/defects/main.fmf
fmfexporter/metadata/requirements/main.fmf
fmfexporter/metadata/testsuite/compatible-topologies.fmf
fmfexporter/metadata/testsuite/main.fmf
fmfexporter/metadata/testsuite/parameters.fmf
fmfexporter/metadata/testsuite/properties.fmf
fmfexporter-0.2.data/scripts/fmfexporter
fmfexporter-0.2.dist-info/LICENSE
fmfexporter-0.2.dist-info/METADATA
fmfexporter-0.2.dist-info/WHEEL
fmfexporter-0.2.dist-info/top_level.txt
fmfexporter-0.2.dist-info/RECORD
