Metadata-Version: 2.1
Name: fmfexporter
Version: 0.2
Summary: Flexible Metadata Format test-case exporter tool
Home-page: https://github.com/rhmessagingqe/fmfexporter
Author: Fernando Giorgetti, Dominik Lenoch
Author-email: fgiorget@redhat.com, dlenoch@redhat.com
License: Apache-2.0
Platform: UNKNOWN
Classifier: Programming Language :: Python :: 3.6
Classifier: License :: OSI Approved :: Apache Software License
Classifier: Operating System :: OS Independent
Provides: fmfexporter
Requires-Python: >=3.6
License-File: LICENSE
Requires-Dist: fmf
Requires-Dist: requests
Requires-Dist: jira
Requires-Dist: urllib3
